gym_quadruped/__init__.py
gym_quadruped/quadruped_env.py
gym_quadruped/robot_cfgs.py
gym_quadruped/data/proprioceptive_datasets.py
gym_quadruped/robot_model/scene_ramp.xml
gym_quadruped/robot_model/scene_slippery.xml
gym_quadruped/robot_model/scene_stairs.xml
gym_quadruped/robot_model/aliengo/aliengo.urdf
gym_quadruped/robot_model/aliengo/aliengo.xml
gym_quadruped/robot_model/aliengo/height_field.png
gym_quadruped/robot_model/aliengo/scene_rough.xml
gym_quadruped/robot_model/aliengo/scene_stairs.xml
gym_quadruped/robot_model/aliengo/assets/calf.stl
gym_quadruped/robot_model/aliengo/assets/hip.stl
gym_quadruped/robot_model/aliengo/assets/thigh.stl
gym_quadruped/robot_model/aliengo/assets/thigh_mirror.stl
gym_quadruped/robot_model/aliengo/assets/trunk.stl
gym_quadruped/robot_model/b2/B2.png
gym_quadruped/robot_model/b2/b2.urdf
gym_quadruped/robot_model/b2/b2.xml
gym_quadruped/robot_model/b2/assets/FL_calf.obj
gym_quadruped/robot_model/b2/assets/FL_foot.obj
gym_quadruped/robot_model/b2/assets/FL_hip.obj
gym_quadruped/robot_model/b2/assets/FL_thigh.obj
gym_quadruped/robot_model/b2/assets/FL_thigh_protect.obj
gym_quadruped/robot_model/b2/assets/FR_calf.obj
gym_quadruped/robot_model/b2/assets/FR_foot.obj
gym_quadruped/robot_model/b2/assets/FR_hip.obj
gym_quadruped/robot_model/b2/assets/FR_thigh.obj
gym_quadruped/robot_model/b2/assets/FR_thigh_protect.obj
gym_quadruped/robot_model/b2/assets/RL_calf.obj
gym_quadruped/robot_model/b2/assets/RL_foot.obj
gym_quadruped/robot_model/b2/assets/RL_hip.obj
gym_quadruped/robot_model/b2/assets/RL_thigh.obj
gym_quadruped/robot_model/b2/assets/RL_thigh_protect.obj
gym_quadruped/robot_model/b2/assets/RR_calf.obj
gym_quadruped/robot_model/b2/assets/RR_foot.obj
gym_quadruped/robot_model/b2/assets/RR_hip.obj
gym_quadruped/robot_model/b2/assets/RR_thigh.obj
gym_quadruped/robot_model/b2/assets/RR_thigh_protect.obj
gym_quadruped/robot_model/b2/assets/base_link.obj
gym_quadruped/robot_model/b2/assets/base_link_lidar.obj
gym_quadruped-1.1.1.dist-info/METADATA
gym_quadruped-1.1.1.dist-info/WHEEL
gym_quadruped-1.1.1.dist-info/RECORD
