Metadata-Version: 2.4
Name: gym-quadruped
Version: 1.1.1
Summary: A gym environment for quadruped robots using MuJoCo physics engine.
Author-email: Daniel Ordoñez-Apraez <daniels.ordonez@gmail.com>, Giulio Turrisi <giulio.turrisi@iit.it>
Maintainer-email: Daniel Felipe Ordoñez Apraez <daniels.ordonez@gmail.com>
Keywords: deep,environment,gym,gymnasium,learning,locomotion,mujoco,quadruped,reinforcement,robotics
Classifier: Development Status :: 5 - Production/Stable
Classifier: Intended Audience :: Developers
Classifier: License :: OSI Approved :: Apache Software License
Classifier: Programming Language :: Python :: 3.10
Classifier: Topic :: Software Development :: Build Tools
Requires-Dist: gym-quadruped>=1.0.2
Requires-Dist: gymnasium
Requires-Dist: h5py
Requires-Dist: mujoco>=3.3.1
Requires-Dist: noise
Requires-Dist: numpy
Requires-Dist: opencv-python
Requires-Dist: pytest
Requires-Dist: robot-descriptions
Requires-Dist: scipy>=1.15.1
